{
  "schemaVersion": 1,
  "id": "tconstruct",
  "version": "${version}",

  "name": "Tinkers' Construct",
  "description": "Tinkers' Construct for Fabric",
  "authors": [
    "kadirac"
  ],
  "contact": {
    "homepage": "https://github.com/kadirac",
    "sources": "https://github.com/kadirac/TinkersConstruct-fabric"
  },

  "license": "MIT",
  "icon": "assets/modid/icon.png",

  "environment": "*",
  "entrypoints": {
    "main": [
      "net.fabricmc.tconstruct.Mod"
    ]
  },

  "depends": {
    "fabricloader": ">=0.14.6",
    "fabric": "*",
    "minecraft": "~1.19",
    "java": ">=17"
  },
  "suggests": {
    "another-mod": "*"
  }
}
